{
  "type": "postprocess_input",
  "name": "",
  "description": "Example Py4Incompact3D Postprocess Input file",
  "mesh": {
    "type": "mesh",
    "name": "mesh_example",
    "description": "Mesh example",
    "properties": {
      "Nx": 256,
      "Ny": 129,
      "Nz": 128,
      "Lx": 12.0,
      "Ly": 2.0,
      "Lz": 4.0,
      "BCx": 0,
      "BCy": 2,
      "BCz": 0,
      "yp" : "/home/paul/DATA/Incompact3d/channel/re180/yp.dat",
      "beta" : 0.259065151,
      "stretched" : 2
    }
  },
	"umean": {
		"type": "data",
		"name": "umean",
		"description": "Mean x velocity",
		"properties": {
			"filename": "/home/paul/DATA/Incompact3d/channel/re180/umean.dat",
			"direction": [0]
		}
	},
	"uumean": {
		"type": "data",
		"name": "uumean",
		"description": "Mean square x velocity",
		"properties": {
			"filename": "/home/paul/DATA/Incompact3d/channel/re180/uumean.dat",
			"direction": [0]
		}
	},
	"vmean": {
		"type": "data",
		"name": "vmean",
		"description": "Mean x velocity",
		"properties": {
			"filename": "/home/paul/DATA/Incompact3d/channel/re180/vmean.dat",
			"direction": [0]
		}
	},
	"vvmean": {
		"type": "data",
		"name": "vvmean",
		"description": "Mean square x velocity",
		"properties": {
			"filename": "/home/paul/DATA/Incompact3d/channel/re180/vvmean.dat",
			"direction": [0]
		}
	},
	"wmean": {
		"type": "data",
		"name": "wmean",
		"description": "Mean x velocity",
		"properties": {
			"filename": "/home/paul/DATA/Incompact3d/channel/re180/wmean.dat",
			"direction": [0]
		}
	},
	"wwmean": {
		"type": "data",
		"name": "wwmean",
		"description": "Mean square x velocity",
		"properties": {
			"filename": "/home/paul/DATA/Incompact3d/channel/re180/wwmean.dat",
			"direction": [0]
		}
	}
}
